{
  "metadata": {
    "asignatura": "Educación Básica Generalista (Primer Ciclo)",
    "nivel": "1° a 3° Básico",
    "fuente_pdf": "Ed_Basica_Generalista.pdf",
    "anio_referencia": 2020,
    "ultima_revision": "2025-11-06",
    "curriculum": "Bases Curriculares 2012/2018 - Ministerio de Educación de Chile",
    "notas": "Temario completo para docentes de primer ciclo que enseñan las 4 asignaturas principales",
    "objetivo_general": "Evaluar conocimientos disciplinares y didácticos para la enseñanza integrada en primer ciclo de Educación Básica"
  },

  "dominios": [
    {
      "id": 1,
      "nombre": "Lenguaje y Comunicación",
      "descripcion": "Comprensión lectora, producción de textos, comunicación oral y estrategias didácticas",
      "porcentaje_evaluacion": 27,
      "subdominios": [
        {
          "nombre": "Contenidos Disciplinares",
          "objetivos": [
            "Identificar características de textos narrativos literarios (cuento, fábula, leyenda, mito)",
            "Reconocer estructura narrativa (narrador, personajes, tiempo, espacio)",
            "Distinguir textos no literarios según propósito (noticia, receta, carta, afiche)",
            "Comprender niveles de comprensión lectora (literal, inferencial, crítico)",
            "Aplicar estrategias de vocabulario contextual",
            "Reconocer elementos de gramática básica (sustantivos, adjetivos, verbos)"
          ],
          "conceptos_clave": [
            "Cuento, fábula, leyenda, mito",
            "Narrador, personajes, tiempo, espacio",
            "Noticia, receta, carta, afiche",
            "Comprensión literal, inferencial, crítica",
            "Vocabulario contextual",
            "Sustantivos, adjetivos, verbos"
          ]
        },
        {
          "nombre": "Enseñanza-Aprendizaje",
          "objetivos": [
            "Aplicar estrategias de comprensión lectora (antes, durante, después)",
            "Implementar proceso de escritura (planificación, textualización, revisión, edición)",
            "Desarrollar conciencia fonológica (silábica y fonémica)",
            "Fomentar comunicación oral efectiva",
            "Utilizar instrumentos de evaluación apropiados",
            "Integrar TIC en aprendizaje del lenguaje"
          ],
          "estrategias": [
            "Lectura compartida y modelada",
            "Activación de conocimientos previos",
            "Preguntas antes/durante/después de lectura",
            "Escritura guiada paso a paso",
            "Juegos de conciencia fonológica",
            "Debate y presentaciones orales",
            "Rúbricas de evaluación formativa"
          ]
        }
      ]
    },
    {
      "id": 2,
      "nombre": "Matemática",
      "descripcion": "Números, operaciones, geometría, datos y estrategias didácticas",
      "porcentaje_evaluacion": 27,
      "subdominios": [
        {
          "nombre": "Contenidos Disciplinares",
          "objetivos": [
            "Comprender propiedades de operaciones (adición y multiplicación)",
            "Trabajar con fracciones (equivalentes, comparación, simplificación)",
            "Reconocer y clasificar ángulos",
            "Calcular perímetro y área de figuras básicas",
            "Representar datos en tablas y gráficos",
            "Resolver problemas en contexto"
          ],
          "conceptos_clave": [
            "Propiedades conmutativa, asociativa, distributiva",
            "Fracciones equivalentes",
            "Ángulo recto, agudo, obtuso",
            "Perímetro y área",
            "Tablas de conteo",
            "Gráficos de barras"
          ]
        },
        {
          "nombre": "Enseñanza-Aprendizaje",
          "objetivos": [
            "Aplicar sistema CPA (Concreto-Pictórico-Abstracto)",
            "Enseñar sistema decimal con material manipulativo",
            "Desarrollar pensamiento matemático",
            "Implementar resolución de problemas",
            "Evaluar formativamente con retroalimentación efectiva"
          ],
          "estrategias": [
            "Material concreto: bloques base 10, regletas",
            "Representaciones pictóricas y diagramas",
            "Modelamiento de problemas",
            "Preguntas metacognitivas",
            "Retroalimentación descriptiva, reflexiva y desafiante"
          ]
        }
      ]
    },
    {
      "id": 3,
      "nombre": "Historia, Geografía y Ciencias Sociales",
      "descripcion": "Pueblos originarios, recursos naturales, ciudadanía y estrategias didácticas",
      "porcentaje_evaluacion": 23,
      "subdominios": [
        {
          "nombre": "Contenidos Disciplinares",
          "objetivos": [
            "Conocer pueblos originarios de Chile (Atacameños, Aymaras, Mapuche, Rapa Nui, Kawésqar)",
            "Distinguir recursos naturales renovables y no renovables",
            "Comprender conceptos democráticos (libertad, igualdad, participación)",
            "Reconocer instituciones fundamentales",
            "Interpretar mapas y planos simples"
          ],
          "conceptos_clave": [
            "5 pueblos originarios principales",
            "Recursos renovables vs no renovables",
            "Libertad, igualdad, participación",
            "Instituciones democráticas",
            "Ubicación espacial",
            "Líneas de tiempo"
          ]
        },
        {
          "nombre": "Enseñanza-Aprendizaje",
          "objetivos": [
            "Desarrollar formación ciudadana activa",
            "Fomentar pensamiento temporal (causa-consecuencia, cambio-continuidad)",
            "Trabajar pensamiento espacial (ubicación, lectura de mapas)",
            "Analizar fuentes históricas apropiadas al nivel",
            "Promover valores democráticos"
          ],
          "estrategias": [
            "Debate y discusión guiada",
            "Estudio de casos reales",
            "Simulaciones y juegos de roles",
            "Proyectos de investigación simple",
            "Análisis de fuentes: identificar, contextualizar, interpretar, evaluar",
            "Construcción de líneas de tiempo",
            "Lectura de mapas y planos"
          ]
        }
      ]
    },
    {
      "id": 4,
      "nombre": "Ciencias Naturales",
      "descripcion": "Seres vivos, universo, investigación científica y estrategias didácticas",
      "porcentaje_evaluacion": 23,
      "subdominios": [
        {
          "nombre": "Contenidos Disciplinares",
          "objetivos": [
            "Clasificar animales (vertebrados: mamíferos, aves, peces, reptiles, anfibios)",
            "Clasificar animales (invertebrados: insectos, arácnidos, crustáceos, moluscos, equinodermos)",
            "Reconocer componentes del universo (estrellas, planetas, satélites)",
            "Comprender el sistema solar",
            "Identificar ciclos de vida de seres vivos"
          ],
          "conceptos_clave": [
            "Vertebrados: 5 tipos",
            "Invertebrados: 5 tipos",
            "Sistema solar: 8 planetas",
            "Estrellas, satélites naturales",
            "Ciclos de vida",
            "Características morfológicas"
          ]
        },
        {
          "nombre": "Enseñanza-Aprendizaje",
          "objetivos": [
            "Implementar investigación científica escolar (observar, preguntar, experimentar, analizar, comunicar)",
            "Desarrollar habilidades de observación sistemática",
            "Realizar experimentos seguros y apropiados",
            "Fomentar clasificación y comparación",
            "Evaluar formativamente el aprendizaje científico"
          ],
          "estrategias": [
            "Observación directa e indirecta",
            "Experimentos simples y seguros",
            "Clasificación de seres vivos",
            "Estudio de ecosistemas cercanos",
            "Modelos del sistema solar",
            "Simulaciones astronómicas",
            "Cuaderno de ciencias",
            "Rúbricas de experimentos",
            "Presentaciones orales de investigaciones"
          ]
        }
      ]
    }
  ],

  "competencias_transversales": {
    "integracion_curricular": {
      "descripcion": "Capacidad de conectar contenidos entre dominios",
      "ejemplos": [
        "Lenguaje + Historia: Análisis de cartas históricas",
        "Matemática + Ciencias: Representación de datos de observaciones",
        "Historia + Ciencias: Recursos naturales de Chile",
        "Lenguaje + Matemática: Resolución de problemas escritos",
        "Lenguaje + Ciencias: Redacción de informes de experimentos",
        "Matemática + Historia: Líneas de tiempo con cálculos"
      ]
    },
    "evaluacion_formativa": {
      "descripcion": "Estrategias de evaluación para el aprendizaje",
      "instrumentos": [
        "Rúbricas con criterios claros",
        "Listas de cotejo observables",
        "Cuadernos de registro",
        "Portafolios de evidencias",
        "Autoevaluación guiada",
        "Coevaluación entre pares"
      ],
      "tipos_retroalimentacion": [
        "Descriptiva: Señala qué está bien y qué mejorar",
        "Reflexiva: Hace preguntas para que el estudiante piense",
        "Desafiante: Propone un reto de nivel superior"
      ]
    },
    "atencion_diversidad": {
      "descripcion": "Diseño Universal para el Aprendizaje (DUA)",
      "principios": [
        "Múltiples formas de representación (visual, auditiva, kinestésica)",
        "Múltiples formas de expresión (oral, escrita, artística)",
        "Múltiples formas de participación (individual, grupal, colaborativa)"
      ]
    }
  },

  "ejemplos_practicos": {
    "lenguaje": {
      "ejemplo_1": {
        "titulo": "Comprensión Lectora Literal",
        "situacion": "Después de leer un cuento sobre un niño que encuentra un perro en el parque",
        "pregunta_adecuada": "¿En qué lugar específico encontró el niño al perro perdido?",
        "explicacion": "Esta pregunta evalúa nivel literal porque la respuesta está explícita en el texto",
        "nivel": "1° básico"
      },
      "ejemplo_2": {
        "titulo": "Proceso de Escritura",
        "situacion": "Un estudiante de 3° básico escribirá una carta a su abuela",
        "paso_inicial": "Pensar qué quiere contarle a su abuela y cómo organizarlo (planificación)",
        "explicacion": "La planificación es el primer paso antes de escribir el borrador",
        "nivel": "3° básico"
      }
    },
    "matematica": {
      "ejemplo_1": {
        "titulo": "Representación CPA",
        "concepto": "Suma de fracciones con igual denominador",
        "concreto": "Usar bloques de patrones o pizzas de fracción",
        "pictórico": "Dibujar representaciones de las fracciones",
        "abstracto": "Escribir el algoritmo numérico 1/4 + 2/4 = 3/4",
        "nivel": "3° básico"
      },
      "ejemplo_2": {
        "titulo": "Resolución de Problemas",
        "problema": "Juan tiene 24 lápices y los quiere repartir equitativamente en 6 estuches. ¿Cuántos lápices irán en cada estuche?",
        "estrategia": "Modelar con material concreto, dibujar, escribir división",
        "nivel": "2° básico"
      }
    },
    "historia": {
      "ejemplo_1": {
        "titulo": "Pueblos Originarios",
        "contenido": "Mapuche",
        "ubicacion": "Zona centro-sur de Chile",
        "caracteristicas": "Agricultores, ganaderos, artesanía en platería",
        "actividad": "Comparar vestimenta tradicional mapuche con otras culturas",
        "nivel": "2° básico"
      },
      "ejemplo_2": {
        "titulo": "Formación Ciudadana",
        "concepto": "Participación democrática",
        "actividad": "Elección de delegado de curso con votación secreta",
        "nivel": "3° básico"
      }
    },
    "ciencias": {
      "ejemplo_1": {
        "titulo": "Clasificación de Animales",
        "actividad": "Observar imágenes de 10 animales diferentes",
        "tarea": "Clasificarlos en vertebrados e invertebrados según sus características",
        "criterios": "Presencia o ausencia de columna vertebral",
        "nivel": "2° básico"
      },
      "ejemplo_2": {
        "titulo": "Investigación Científica",
        "pregunta": "¿Qué tipo de plantas crecen mejor con luz solar directa?",
        "etapas": "Observar, formular hipótesis, experimentar durante 2 semanas, registrar datos, analizar resultados, comunicar",
        "nivel": "3° básico"
      }
    }
  },

  "orientaciones_evaluacion": {
    "distribucion_recomendada": {
      "lenguaje": "8 preguntas (27%)",
      "matematica": "8 preguntas (27%)",
      "historia": "7 preguntas (23%)",
      "ciencias": "7 preguntas (23%)"
    },
    "tipos_pregunta": [
      {
        "tipo": "Conocimiento disciplinar",
        "descripcion": "Evalúa dominio de contenidos específicos de cada asignatura",
        "porcentaje": "40%"
      },
      {
        "tipo": "Estrategias didácticas",
        "descripcion": "Evalúa conocimiento de metodologías de enseñanza apropiadas",
        "porcentaje": "30%"
      },
      {
        "tipo": "Evaluación formativa",
        "descripcion": "Evalúa capacidad de evaluar y retroalimentar aprendizajes",
        "porcentaje": "15%"
      },
      {
        "tipo": "Integración curricular",
        "descripcion": "Evalúa capacidad de conectar contenidos entre asignaturas",
        "porcentaje": "15%"
      }
    ],
    "conexiones_pruebas": [
      {
        "codigo_prueba": "63-sc-l",
        "notas": "Contenidos de Lenguaje del dominio 1 se relacionan con esta prueba específica"
      },
      {
        "codigo_prueba": "66-sc-m",
        "notas": "Contenidos de Matemática del dominio 2 se relacionan con esta prueba específica"
      },
      {
        "codigo_prueba": "71-sc-cs",
        "notas": "Contenidos de Historia del dominio 3 se relacionan con esta prueba específica"
      }
    ]
  },

  "recursos_apoyo": {
    "materiales": [
      "Bloques base 10 y regletas Cuisenaire",
      "Textos literarios apropiados para 1° a 3° básico",
      "Mapas de Chile y mapamundi",
      "Materiales para experimentos científicos",
      "Recursos digitales y TIC",
      "Juegos educativos por asignatura"
    ],
    "bibliografia": [
      "Bases Curriculares de Educación Básica (MINEDUC 2012/2018)",
      "Programas de Estudio 1° a 3° básico",
      "Marco para la Buena Enseñanza",
      "Estándares Orientadores para Carreras de Pedagogía"
    ]
  },

  "consejos_preparacion": [
    "Revisar Bases Curriculares 2012/2018 para 1° a 3° básico",
    "Practicar integración de contenidos entre asignaturas",
    "Dominar estrategias didácticas específicas (CPA, comprensión lectora, etc.)",
    "Familiarizarse con instrumentos de evaluación formativa",
    "Estudiar ejemplos de planificaciones integradas",
    "Practicar análisis de situaciones pedagógicas reales",
    "Conocer características del desarrollo infantil 6-9 años",
    "Revisar errores conceptuales comunes en estudiantes"
  ]
}
